pysparkbundle/PySparkBundle.py
pysparkbundle/PySparkBundleTest.py
pysparkbundle/_config/.gitignore
pysparkbundle/_config/config.yaml
pysparkbundle/_config/config_test.yaml
pysparkbundle/csv/csv_append.py
pysparkbundle/csv/csv_overwrite.py
pysparkbundle/csv/csv_reader.py
pysparkbundle/csv/csv_write_errorifexists.py
pysparkbundle/csv/csv_write_ignore.py
pysparkbundle/csv/lineage/CsvRead.py
pysparkbundle/dataframe/DataFrameShowMethod.py
pysparkbundle/dataframe/DataFrameShowMethodInjector.py
pysparkbundle/dataframe/DataFrameShowMethodInterface.py
pysparkbundle/delta/delta_append.py
pysparkbundle/delta/delta_overwrite.py
pysparkbundle/delta/delta_reader.py
pysparkbundle/delta/delta_write_errorifexists.py
pysparkbundle/delta/delta_write_ignore.py
pysparkbundle/delta/lineage/DeltaRead.py
pysparkbundle/filesystem/DummyFilesystem.py
pysparkbundle/filesystem/FilesystemInjector.py
pysparkbundle/filesystem/FilesystemInterface.py
pysparkbundle/jdbc/OptionsFactoryInterface.py
pysparkbundle/jdbc/TableReader.py
pysparkbundle/json/json_append.py
pysparkbundle/json/json_overwrite.py
pysparkbundle/json/json_reader.py
pysparkbundle/json/json_write_errorifexists.py
pysparkbundle/json/json_write_ignore.py
pysparkbundle/json/lineage/JsonRead.py
pysparkbundle/lineage/FileRead.py
pysparkbundle/lineage/PathWriter.py
pysparkbundle/lineage/PathWriterParser.py
pysparkbundle/lineage/argument/ArgumentMapping.py
pysparkbundle/parquet/lineage/ParquetRead.py
pysparkbundle/parquet/parquet_append.py
pysparkbundle/parquet/parquet_overwrite.py
pysparkbundle/parquet/parquet_reader.py
pysparkbundle/parquet/parquet_write_errorifexists.py
pysparkbundle/parquet/parquet_write_ignore.py
pysparkbundle/read/PathReader.py
pysparkbundle/test/DummySparkFactory.py
pysparkbundle/test/PySparkTestCase.py
pysparkbundle/write/PathWriter.py
pysparkbundle/write/PathWriterDecorator.py
pyspark_bundle-1.2.3.dist-info/entry_points.txt
pyspark_bundle-1.2.3.dist-info/LICENSE
pyspark_bundle-1.2.3.dist-info/WHEEL
pyspark_bundle-1.2.3.dist-info/METADATA
pyspark_bundle-1.2.3.dist-info/RECORD
