Metadata-Version: 2.1
Name: pyspark-bundle
Version: 1.2.3
Summary: PySpark bundle for the Daipe Framework
Home-page: https://github.com/daipe-ai/pyspark-bundle
License: MIT
Author: Jiri Koutny
Author-email: jiri.koutny@datasentics.com
Requires-Python: >=3.7,<4.0
Classifier: License :: OSI Approved :: MIT License
Classifier: Operating System :: OS Independent
Classifier: Programming Language :: Python :: 3
Classifier: Programming Language :: Python :: 3.7
Classifier: Programming Language :: Python :: 3.8
Classifier: Programming Language :: Python :: 3.9
Requires-Dist: daipe-core (>=1.3.2,<2.0.0)
Requires-Dist: injecta (>=0.10.0,<0.11.0)
Requires-Dist: pyfony-bundles (>=0.4.0,<0.5.0)
Project-URL: Repository, https://github.com/daipe-ai/pyspark-bundle
